[
    {
        "key": "group_686e4a9443891",
        "title": "Lead",
        "fields": [
            {
                "key": "field_686e4a95bfca5",
                "label": "Firstname",
                "name": "firstname",
                "aria-label": "",
                "type": "text",
                "instructions": "",
                "required": 0,
                "conditional_logic": 0,
                "wrapper": {
                    "width": "",
                    "class": "",
                    "id": ""
                },
                "default_value": "",
                "maxlength": "",
                "allow_in_bindings": 0,
                "placeholder": "",
                "prepend": "",
                "append": ""
            },
            {
                "key": "field_686e4dd8bfca6",
                "label": "Lastname",
                "name": "lastname",
                "aria-label": "",
                "type": "text",
                "instructions": "",
                "required": 0,
                "conditional_logic": 0,
                "wrapper": {
                    "width": "",
                    "class": "",
                    "id": ""
                },
                "default_value": "",
                "maxlength": "",
                "allow_in_bindings": 0,
                "placeholder": "",
                "prepend": "",
                "append": ""
            },
            {
                "key": "field_686e4de1bfca7",
                "label": "Email",
                "name": "email",
                "aria-label": "",
                "type": "email",
                "instructions": "",
                "required": 0,
                "conditional_logic": 0,
                "wrapper": {
                    "width": "",
                    "class": "",
                    "id": ""
                },
                "default_value": "",
                "allow_in_bindings": 0,
                "placeholder": "",
                "prepend": "",
                "append": ""
            },
            {
                "key": "field_686e4dfcbfca8",
                "label": "Mobile",
                "name": "mobile",
                "aria-label": "",
                "type": "text",
                "instructions": "",
                "required": 0,
                "conditional_logic": 0,
                "wrapper": {
                    "width": "",
                    "class": "",
                    "id": ""
                },
                "default_value": "",
                "maxlength": "",
                "allow_in_bindings": 0,
                "placeholder": "",
                "prepend": "",
                "append": ""
            },
            {
                "key": "field_686e4e14bfca9",
                "label": "Society",
                "name": "society",
                "aria-label": "",
                "type": "text",
                "instructions": "",
                "required": 0,
                "conditional_logic": 0,
                "wrapper": {
                    "width": "",
                    "class": "",
                    "id": ""
                },
                "default_value": "",
                "maxlength": "",
                "allow_in_bindings": 0,
                "placeholder": "",
                "prepend": "",
                "append": ""
            },
            {
                "key": "field_686e4e23bfcaa",
                "label": "Post",
                "name": "post",
                "aria-label": "",
                "type": "text",
                "instructions": "",
                "required": 0,
                "conditional_logic": 0,
                "wrapper": {
                    "width": "",
                    "class": "",
                    "id": ""
                },
                "default_value": "",
                "maxlength": "",
                "allow_in_bindings": 0,
                "placeholder": "",
                "prepend": "",
                "append": ""
            },
            {
                "key": "field_686e5c60ca38a",
                "label": "Contact datetime",
                "name": "contact_datetime",
                "aria-label": "",
                "type": "date_time_picker",
                "instructions": "",
                "required": 0,
                "conditional_logic": 0,
                "wrapper": {
                    "width": "",
                    "class": "",
                    "id": ""
                },
                "display_format": "Y-m-d H:i:s",
                "return_format": "Y-m-d H:i:s",
                "first_day": 1,
                "allow_in_bindings": 0
            },
            {
                "key": "field_686eb64ea4f14",
                "label": "Linked virtual card",
                "name": "linked_virtual_card",
                "aria-label": "",
                "type": "relationship",
                "instructions": "",
                "required": 0,
                "conditional_logic": 0,
                "wrapper": {
                    "width": "",
                    "class": "",
                    "id": ""
                },
                "post_type": [
                    "virtual_card"
                ],
                "post_status": "",
                "taxonomy": "",
                "filters": [
                    "search",
                    "post_type",
                    "taxonomy"
                ],
                "return_format": "id",
                "min": "",
                "max": "",
                "allow_in_bindings": 0,
                "elements": "",
                "bidirectional": 0,
                "bidirectional_target": []
            }
        ],
        "location": [
            [
                {
                    "param": "post_type",
                    "operator": "==",
                    "value": "lead"
                }
            ]
        ],
        "menu_order": 0,
        "position": "normal",
        "style": "default",
        "label_placement": "top",
        "instruction_placement": "label",
        "hide_on_screen": "",
        "active": true,
        "description": "",
        "show_in_rest": 0
    }
]
